Metadata-Version: 2.1
Name: combinatoricsResolver
Version: 0.0.1
Summary: Solve Combinatorcs related problems
Home-page: 
Author: Harsh Verma
Author-email: b220024@iiit-bh.ac.in
License: MIT
Keywords: combinatorics
Classifier: Development Status :: 5 - Production/Stable
Classifier: Intended Audience :: Education
Classifier: Operating System :: Microsoft :: Windows :: Windows 11
Classifier: License :: OSI Approved :: MIT License
Classifier: Programming Language :: Python :: 3
License-File: LICENCE.txt
